memorylayer/__init__.py
memorylayer/client.py
memorylayer/exceptions.py
memorylayer/http_client.py
memorylayer/types.py
memorylayer/resources/__init__.py
memorylayer/resources/graph.py
memorylayer/resources/ingest.py
memorylayer/resources/memories.py
memorylayer/resources/router.py
memorylayer/resources/search.py
memorylayerai-0.5.0.dist-info/METADATA
memorylayerai-0.5.0.dist-info/WHEEL
memorylayerai-0.5.0.dist-info/licenses/LICENSE
memorylayerai-0.5.0.dist-info/RECORD
